descriptive_analysis_beginners/__init__.py
descriptive_analysis_beginners/functions.py
descriptive_analysis_beginners-0.0.1.dist-info/METADATA
descriptive_analysis_beginners-0.0.1.dist-info/WHEEL
descriptive_analysis_beginners-0.0.1.dist-info/licenses/LICENSE
descriptive_analysis_beginners-0.0.1.dist-info/RECORD
