Metadata-Version: 2.1
Name: descriptive_analysis_beginners
Version: 0.0.1
Summary: A descriptive analysis package whith statistics and visualizations
Project-URL: Homepage, https://github.com/nagorebermeosolo/descriptive_analysis_beginners
Project-URL: Bug Tracker, https://github.com/nagorebermeosolo/descriptive_analysis_beginners/issues
Author-email: Nagore y Ainhoa <nagore.bermeosolo@alumni.mondragon.edu>
License-File: LICENSE
Classifier: License :: OSI Approved :: MIT License
Classifier: Operating System :: OS Independent
Classifier: Programming Language :: Python :: 3
Requires-Python: >=3.7
